{"pages": {"Rivers": "https://raw.githubusercontent.com/lukefullard/State_and_Trends_Reporting/main/scripts_and_settings/Rivers_sites.json", "Lakes": "https://raw.githubusercontent.com/lukefullard/State_and_Trends_Reporting/main/scripts_and_settings/Lakes_sites.json", "Contact_Recreation": "https://raw.githubusercontent.com/lukefullard/State_and_Trends_Reporting/main/scripts_and_settings/Contact_Recreation_sites.json"}, "spatial_files": {"District": "https://raw.githubusercontent.com/lukefullard/State_and_Trends_Reporting/main/scripts_and_settings/District_spatial_data.json", "Freshwater Management Unit": "https://raw.githubusercontent.com/lukefullard/State_and_Trends_Reporting/main/scripts_and_settings/Freshwater%20Management%20Unit_spatial_data.json", "Water management Zone": "https://raw.githubusercontent.com/lukefullard/State_and_Trends_Reporting/main/scripts_and_settings/Water%20management%20Zone_spatial_data.json", "Water management Subzone": "https://raw.githubusercontent.com/lukefullard/State_and_Trends_Reporting/main/scripts_and_settings/Water%20management%20Subzone_spatial_data.json"}, "sidebar_image": "https://raw.githubusercontent.com/lukefullard/State_and_Trends_Reporting/main/assets/SidebarTitle.png", "state_data": "https://raw.githubusercontent.com/lukefullard/State_and_Trends_Reporting/main/state_results/", "raw_data": "https://raw.githubusercontent.com/lukefullard/State_and_Trends_Reporting/main/data/", "x_column": "NZTM.X", "y_column": "NZTM.Y", "epsg_code": 2193, "geospatial_regions": ["District", "Freshwater Management Unit", "Water management Zone", "Water management Subzone"], "add_nof_grade_background_colours": true, "nof_grade_colours": {"Very Good": "#2abeff", "Good": "#aed77a", "Fair": "#e6e600", "Poor": "#ff6767", "Very Poor": "#ff6767", "A": "#2abeff", "B": "#aed77a", "C": "#e6e600", "D": "#ffa74d", "E": "#ff6767"}, "nof_grade_colourblind_colours": {"Very Good": "#3DB7E9", "Good": "#359B73", "Fair": "#F0E442", "Poor": "#F748A5", "Very Poor": "#F748A5", "A": "#3DB7E9", "B": "#359B73", "C": "#F0E442", "D": "#E69F00", "E": "#F748A5"}, "nof_grade_baselines": {"ASPM": "D", "Chlorophyll A (92nd Percentile)": "D", "Chlorophyll A (83rd Percentile)": "D", "Chlorophyll A (Median)": "D", "Chlorophyll A (Annual Maximum)": "D", "MCI": "D", "Ammoniacal-N (Median)": "C", "Ammoniacal-N (95th Percentile)": "C", "Nitrate-N (Median)": "C", "Nitrate-N (95th Percentile)": "C", "QMCI": "D", "Visual Clarity (Sediment class 1)": "D", "Visual Clarity (Sediment class 2)": "D", "Visual Clarity (Sediment class 3)": "D", "Visual Clarity (Sediment class 4)": "D", "E. coli (Primary Contact)": "Poor"}, "nof_band_definitions": {"Rivers": {"ASPM": {"bins": [0, 0.2999999, 0.39999999, 0.59999999, 1000000000], "labels": ["D", "C", "B", "A"]}, "Chlorophyll A (92nd Percentile)": {"bins": [0, 50, 120, 200, 100000], "labels": ["A", "B", "C", "D"]}, "Chlorophyll A (83rd Percentile)": {"bins": [0, 50, 120, 200, 100000], "labels": ["A", "B", "C", "D"]}, "DRP (Median)": {"bins": [0, 0.006, 0.01, 0.018, 1000000], "labels": ["A", "B", "C", "D"]}, "DRP (95th Percentile)": {"bins": [0, 0.021, 0.03, 0.054, 1000000], "labels": ["A", "B", "C", "D"]}, "E coli (>260)": {"bins": [0, 19.99999, 29.99999, 33.999999, 49.999999, 101], "labels": ["A", "B", "C", "D", "E"]}, "E coli (>540)": {"bins": [0, 4.999999, 9.999999, 19.999999, 29.999999, 101], "labels": ["A", "B", "C", "D", "E"]}, "E coli (Median)": {"bins": [0, 130, 260, 100000000], "labels": ["A", "D", "E"]}, "E coli (95th Percentile)": {"bins": [0, 540, 1000, 1200, 10000000000], "labels": ["A", "B", "C", "E"]}, "MCI": {"bins": [0, 89.999999, 109.9999999, 129.999999, 100000000], "labels": ["D", "C", "B", "A"]}, "Ammoniacal-N (95th Percentile)": {"bins": [0, 0.05, 0.4, 2.2, 100000], "labels": ["A", "B", "C", "D"]}, "Ammoniacal-N (Median)": {"bins": [0, 0.03, 0.24, 1.3, 100000], "labels": ["A", "B", "C", "D"]}, "Nitrate-N (Median)": {"bins": [0, 1, 2.4, 6.9, 100000], "labels": ["A", "B", "C", "D"]}, "Nitrate-N (95th Percentile)": {"bins": [0, 1.5, 3.5, 9.8, 100000], "labels": ["A", "B", "C", "D"]}, "QMCI": {"bins": [0, 4.4999999, 5.4999999, 6.4999999, 10000000], "labels": ["D", "C", "B", "A"]}, "Visual Clarity (Sediment class 1)": {"bins": [0, 1.33999999, 1.54999999, 1.77999999, 100000], "labels": ["D", "C", "B", "A"]}, "Visual Clarity (Sediment class 2)": {"bins": [0, 0.60999999, 0.75999999, 0.92999999, 100000], "labels": ["D", "C", "B", "A"]}, "Visual Clarity (Sediment class 3)": {"bins": [0, 2.21999999, 2.56999999, 2.94999999, 100000], "labels": ["D", "C", "B", "A"]}, "Visual Clarity (Sediment class 4)": {"bins": [0, 0.97999999, 1.16999999, 1.37999999, 100000], "labels": ["D", "C", "B", "A"]}}, "Lakes": {"Cyanobacteria Biovolume (80th percentile)": {"bins": [0, 0.5, 1, 1.8, 10000000], "labels": ["A", "B", "C", "D"]}, "Chlorophyll A (Median)": {"bins": [0, 2, 5, 12, 10000], "labels": ["A", "B", "C", "D"]}, "Chlorophyll A (Annual Maximum)": {"bins": [0, 10, 25, 60, 100000], "labels": ["A", "B", "C", "D"]}, "E coli (>260)": {"bins": [0, 19.99999, 29.99999, 33.999999, 49.999999, 101], "labels": ["A", "B", "C", "D", "E"]}, "E coli (>540)": {"bins": [0, 4.999999, 9.999999, 19.999999, 29.999999, 101], "labels": ["A", "B", "C", "D", "E"]}, "E coli (Median)": {"bins": [0, 130, 260, 100000000], "labels": ["A", "D", "E"]}, "E coli (95th Percentile)": {"bins": [0, 540, 1000, 1200, 10000000000], "labels": ["A", "B", "C", "E"]}, "Ammoniacal-N (95th Percentile)": {"bins": [0, 0.05, 0.4, 2.2, 100000], "labels": ["A", "B", "C", "D"]}, "Ammoniacal-N (Median)": {"bins": [0, 0.03, 0.24, 1.3, 100000], "labels": ["A", "B", "C", "D"]}, "Total Nitrogen (Median, stratified)": {"bins": [0, 160, 350, 750, 100000], "labels": ["A", "B", "C", "D"]}, "Total Nitrogen (Median, polymictic)": {"bins": [0, 300, 500, 800, 100000], "labels": ["A", "B", "C", "D"]}, "Total Phosphorus (Median)": {"bins": [0, 10, 20, 50, 100000], "labels": ["A", "B", "C", "D"]}}, "Contact Recreation": {"E coli (>260)": {"bins": [0, 19.99999, 29.99999, 33.999999, 49.999999, 101], "labels": ["A", "B", "C", "D", "E"]}, "E coli (>540)": {"bins": [0, 4.999999, 9.999999, 19.999999, 29.999999, 101], "labels": ["A", "B", "C", "D", "E"]}, "E coli (Median)": {"bins": [0, 130, 260, 100000000], "labels": ["A", "D", "E"]}, "E coli (95th Percentile)": {"bins": [0, 540, 1000, 1200, 10000000000], "labels": ["A", "B", "C", "E"]}, "E. coli (Primary Contact)": {"bins": [0, 130, 260, 540, 1000000000000], "labels": ["Excellent", "Good", "Fair", "Poor"]}}}, "nof_attribute_statistics": {"ASPM": "Median over summer period", "Cyanobacteria Biovolume (80th percentile)": "80th percentile", "Chlorophyll A (92nd Percentile)": "92nd percentile", "Chlorophyll A (83rd Percentile)": "83rd percentile", "Chlorophyll A (Median)": "Median", "Chlorophyll A (Annual Maximum)": "Annual Maximum", "DRP (Median)": "Median", "DRP (95th Percentile)": "95th percentile", "E coli (>260)": "percentage of samples > 260 MPN", "E coli (>540)": "percentage of samples > 540 MPN", "E coli (Median)": "Median", "E coli (95th Percentile)": "95th percentile", "E. coli (Primary Contact)": "95th percentile", "MCI": "Median over summer period", "Ammoniacal-N (95th Percentile)": "95th percentile", "Ammoniacal-N (Median)": "Median", "Nitrate-N (Median)": "Median", "Nitrate-N (95th Percentile)": "95th percentile", "QMCI": "Median over summer period", "Visual Clarity (Sediment class 1)": "Median", "Visual Clarity (Sediment class 2)": "Median", "Visual Clarity (Sediment class 3)": "Median", "Visual Clarity (Sediment class 4)": "Median", "Soluble Inorganic Nitrogen (Median)": "Median", "Soluble Inorganic Nitrogen (95th Percentile)": "95th percentile", "Total Nitrogen (Median, stratified)": "Median", "Total Nitrogen (Median, polymictic)": "Median", "Total Nitrogen (Median)": "Median", "Total Nitrogen (95th Percentile)": "95th percentile", "Total Phosphorus (95th Percentile)": "95th percentile", "Total Phosphorus (Median)": "Median", "pH (Median)": "Median"}, "polymictic_lakes": ["Lake Alice", "Lake Alice (Composite)", "Lake Heaton", "Lake Heaton (Composite)", "Lake Herbert", "Lake Herbert (Composite)", "Lake Horowhenua at Buoy", "Lake Horowhenua Composite", "Lake Koitiata", "Lake Koitiata (Composite)", "Lake Koputara", "Lake Koputara (Composite)", "Lake Poroa (Composite)", "Lake Waipu", "Lake Waipu (Composite)", "Lake Westmere", "Lake Westmere (Composite)", "Lake William (Composite)", "Lake William", "Omanuka Lagoon", "Omanuka Lagoon (Composite)", "Pukepuke Lagoon", "Pukepuke Lagoon (Composite)", "Hokowhitu Lagoon at Walkbridge", "Lake Papaitonga at Staff Gauge"]}